netflix_update_notify.py
netflix_update_notify-0.2.2.dist-info/METADATA
netflix_update_notify-0.2.2.dist-info/WHEEL
netflix_update_notify-0.2.2.dist-info/top_level.txt
netflix_update_notify-0.2.2.dist-info/RECORD
