Metadata-Version: 2.1
Name: netflix-update-notify
Version: 0.2.2
Summary: Introduction
Home-page: https://stash.corp.netflix.com/projects/~DAVIDB/repos/netflix_update_notify/browse
Author: TSC
Author-email: davidb@netflix.com
License: UNKNOWN
Keywords: netflix_update_notify
Platform: UNKNOWN
Requires-Python: >=3.7
Requires-Dist: requests
Requires-Dist: pkg-info
Requires-Dist: semver
Requires-Dist: importlib-metadata ; python_version < "3.8"
Provides-Extra: test
Requires-Dist: tox ; extra == 'test'
